{
  "project_info": {
    "project_number": "482633070695",
    "project_id": "asteroids-52528",
    "storage_bucket": "asteroids-52528.firebasestorage.app"
  },
  "client": [
    {
      "client_info": {
        "mobilesdk_app_id": "1:482633070695:android:78cd606720dc08c71c7cc2",
        "android_client_info": {
          "package_name": "com.DefaultCompany.Asteroids"
        }
      },
      "oauth_client": [],
      "api_key": [
        {
          "current_key": "AIzaSyBY7q0CLX0wEv-r351V9wOz5AK3JZeoF1w"
        }
      ],
      "services": {
        "appinvite_service": {
          "other_platform_oauth_client": []
        }
      }
    }
  ],
  "configuration_version": "1"
}